htmlishell/__init__.py
htmlishell/__main__.py
htmlishell/parsing.py
htmlishell-0.2.0.dist-info/LICENSE
htmlishell-0.2.0.dist-info/METADATA
htmlishell-0.2.0.dist-info/WHEEL
htmlishell-0.2.0.dist-info/entry_points.txt
htmlishell-0.2.0.dist-info/RECORD
